{"id":"Arm0","timelines":[{"type":0,"tacks":[{"start":12,"span":8,"type":0,"pos":"{\"head\":{\"pos\":{\"x\":0,\"y\":0},\"curveX\":0,\"curveY\":0},\"body\":{\"pos\":{\"x\":0,\"y\":0},\"curveX\":0,\"curveY\":0},\"leftArm\":{\"pos\":{\"x\":0,\"y\":0},\"curveX\":0,\"curveY\":0},\"rightArm\":{\"pos\":{\"x\":4,\"y\":0},\"curveX\":0,\"curveY\":0},\"leftHand\":{\"pos\":{\"x\":3,\"y\":3},\"curveX\":0,\"curveY\":0},\"rightHand\":{\"pos\":{\"x\":3,\"y\":-1},\"curveX\":0,\"curveY\":0},\"leftLeg\":{\"pos\":{\"x\":-3,\"y\":0},\"curveX\":0,\"curveY\":0},\"rightLeg\":{\"pos\":{\"x\":6,\"y\":2},\"curveX\":0,\"curveY\":0},\"leftFoot\":{\"pos\":{\"x\":-3,\"y\":0},\"curveX\":0,\"curveY\":0},\"rightFoot\":{\"pos\":{\"x\":11,\"y\":6},\"curveX\":0,\"curveY\":0},\"ant\":{\"pos\":{\"x\":0,\"y\":0},\"curveX\":0,\"curveY\":0}}"},{"start":4,"span":8,"type":0,"pos":"{\"head\":{\"pos\":{\"x\":0,\"y\":0},\"curveX\":0,\"curveY\":0},\"body\":{\"pos\":{\"x\":0,\"y\":0},\"curveX\":0,\"curveY\":0},\"leftArm\":{\"pos\":{\"x\":2,\"y\":1},\"curveX\":0,\"curveY\":0},\"rightArm\":{\"pos\":{\"x\":0,\"y\":0},\"curveX\":0,\"curveY\":0},\"leftHand\":{\"pos\":{\"x\":6,\"y\":4},\"curveX\":0,\"curveY\":0},\"rightHand\":{\"pos\":{\"x\":0,\"y\":3},\"curveX\":0,\"curveY\":0},\"leftLeg\":{\"pos\":{\"x\":1,\"y\":0},\"curveX\":0,\"curveY\":0},\"rightLeg\":{\"pos\":{\"x\":0,\"y\":0},\"curveX\":0,\"curveY\":0},\"leftFoot\":{\"pos\":{\"x\":2,\"y\":0},\"curveX\":0,\"curveY\":0},\"rightFoot\":{\"pos\":{\"x\":-1,\"y\":0},\"curveX\":0,\"curveY\":0},\"ant\":{\"pos\":{\"x\":0,\"y\":7},\"curveX\":0,\"curveY\":0}}"},{"start":20,"span":8,"type":0,"pos":"{\"head\":{\"pos\":{\"x\":0,\"y\":0},\"curveX\":0,\"curveY\":0},\"body\":{\"pos\":{\"x\":0,\"y\":0},\"curveX\":0,\"curveY\":0},\"leftArm\":{\"pos\":{\"x\":0,\"y\":2},\"curveX\":0,\"curveY\":0},\"rightArm\":{\"pos\":{\"x\":2,\"y\":2},\"curveX\":0,\"curveY\":0},\"leftHand\":{\"pos\":{\"x\":2,\"y\":10},\"curveX\":0,\"curveY\":0},\"rightHand\":{\"pos\":{\"x\":2,\"y\":10},\"curveX\":0,\"curveY\":0},\"leftLeg\":{\"pos\":{\"x\":1,\"y\":0},\"curveX\":0,\"curveY\":0},\"rightLeg\":{\"pos\":{\"x\":0,\"y\":0},\"curveX\":0,\"curveY\":0},\"leftFoot\":{\"pos\":{\"x\":2,\"y\":0},\"curveX\":0,\"curveY\":0},\"rightFoot\":{\"pos\":{\"x\":-1,\"y\":0},\"curveX\":0,\"curveY\":0},\"ant\":{\"pos\":{\"x\":0,\"y\":7},\"curveX\":0,\"curveY\":0}}"},{"start":0,"span":4,"type":0,"pos":"{\"head\":{\"pos\":{\"x\":0,\"y\":0},\"curveX\":0,\"curveY\":0},\"body\":{\"pos\":{\"x\":0,\"y\":0},\"curveX\":0,\"curveY\":0},\"leftArm\":{\"pos\":{\"x\":0,\"y\":0},\"curveX\":0,\"curveY\":0},\"rightArm\":{\"pos\":{\"x\":0,\"y\":0},\"curveX\":0,\"curveY\":0},\"leftHand\":{\"pos\":{\"x\":0,\"y\":0},\"curveX\":0,\"curveY\":0},\"rightHand\":{\"pos\":{\"x\":0,\"y\":0},\"curveX\":0,\"curveY\":0},\"leftLeg\":{\"pos\":{\"x\":0,\"y\":0},\"curveX\":0,\"curveY\":0},\"rightLeg\":{\"pos\":{\"x\":0,\"y\":0},\"curveX\":0,\"curveY\":0},\"leftFoot\":{\"pos\":{\"x\":0,\"y\":0},\"curveX\":0,\"curveY\":0},\"rightFoot\":{\"pos\":{\"x\":0,\"y\":0},\"curveX\":0,\"curveY\":0},\"ant\":{\"pos\":{\"x\":0,\"y\":0},\"curveX\":0,\"curveY\":0}}"}]}]}